collibra_catalog_classification/__init__.py
collibra_catalog_classification/api_client.py
collibra_catalog_classification/configuration.py
collibra_catalog_classification/rest.py
collibra_catalog_classification/api/__init__.py
collibra_catalog_classification/api/data_classification_api.py
collibra_catalog_classification/models/__init__.py
collibra_catalog_classification/models/add_classification_match_request.py
collibra_catalog_classification/models/add_classification_matches_request.py
collibra_catalog_classification/models/add_classification_request.py
collibra_catalog_classification/models/change_classification_match_request.py
collibra_catalog_classification/models/change_classification_request.py
collibra_catalog_classification/models/classification.py
collibra_catalog_classification/models/classification_match.py
collibra_catalog_classification/models/classify_request.py
collibra_catalog_classification/models/delete_classification_matches_request.py
collibra_catalog_classification/models/find_classification_matches_request.py
collibra_catalog_classification/models/find_classifications_request.py
collibra_catalog_classification/models/job.py
collibra_catalog_classification/models/named_resource_reference_impl.py
collibra_catalog_classification/models/paged_response_classification.py
collibra_catalog_classification/models/paged_response_classification_match.py
test/__init__.py
test/test_add_classification_match_request.py
test/test_add_classification_matches_request.py
test/test_add_classification_request.py
test/test_change_classification_match_request.py
test/test_change_classification_request.py
test/test_classification.py
test/test_classification_match.py
test/test_classify_request.py
test/test_data_classification_api.py
test/test_delete_classification_matches_request.py
test/test_find_classification_matches_request.py
test/test_find_classifications_request.py
test/test_job.py
test/test_named_resource_reference_impl.py
collibra_catalog_classification_100-1.0.0.dist-info/METADATA
collibra_catalog_classification_100-1.0.0.dist-info/WHEEL
collibra_catalog_classification_100-1.0.0.dist-info/top_level.txt
collibra_catalog_classification_100-1.0.0.dist-info/RECORD
