Metadata-Version: 2.1
Name: collibra-catalog-classification-100
Version: 1.0.0
Summary: Collibra Catalog Classification API
Home-page: 
Author-email: 
Keywords: Swagger,Collibra Catalog Classification API
Requires-Dist: urllib3 (>=1.15)
Requires-Dist: six (>=1.10)
Requires-Dist: certifi
Requires-Dist: python-dateutil
